multilingual_python/__init__.py
multilingual_python/src/__init__.py
multilingual_python/src/pre_process.py
multilingual_python/src/run_cli.py
multilingual_python-0.0.10.dist-info/METADATA
multilingual_python-0.0.10.dist-info/WHEEL
multilingual_python-0.0.10.dist-info/top_level.txt
multilingual_python-0.0.10.dist-info/RECORD
